foresight_lib_py/__init__.py
foresight_lib_py/data.py
foresight_lib_py/graph.py
foresight_lib_py/http.py
foresight_lib_py/py.typed
foresight_lib_py-0.1.0.dist-info/METADATA
foresight_lib_py-0.1.0.dist-info/WHEEL
foresight_lib_py-0.1.0.dist-info/RECORD
