Metadata-Version: 2.3
Name: foresight-lib-py
Version: 0.1.0
Summary: Foresight Library for Python
Author-email: Tim Jagenberg <tim.jagenberg@piscada.com>
Requires-Python: >=3.12
Requires-Dist: authlib>=1.3.2
Requires-Dist: gql[httpx]>=3.5.0
Requires-Dist: pandas>=2.2.3
